{"frames": {

"basePanelLemon":
{
	"frame": {"x":1777,"y":748,"w":151,"h":130},
	"rotated": false,
	"trimmed": false,
	"spriteSourceSize": {"x":0,"y":0,"w":151,"h":130},
	"sourceSize": {"w":151,"h":130},
	"anchor": {"x":0.5,"y":0.5}
},
"glassLemonAnim/glassAnimationLemon01":
{
	"frame": {"x":1583,"y":1089,"w":105,"h":122},
	"rotated": true,
	"trimmed": true,
	"spriteSourceSize": {"x":7,"y":52,"w":105,"h":122},
	"sourceSize": {"w":119,"h":176},
	"anchor": {"x":0.5,"y":0.7}
},
"glassLemonAnim/glassAnimationLemon02":
{
	"frame": {"x":333,"y":1134,"w":106,"h":135},
	"rotated": false,
	"trimmed": true,
	"spriteSourceSize": {"x":6,"y":38,"w":106,"h":135},
	"sourceSize": {"w":119,"h":176},
	"anchor": {"x":0.5,"y":0.7}
},
"glassLemonAnim/glassAnimationLemon03":
{
	"frame": {"x":980,"y":686,"w":106,"h":156},
	"rotated": true,
	"trimmed": true,
	"spriteSourceSize": {"x":4,"y":18,"w":106,"h":156},
	"sourceSize": {"w":119,"h":176},
	"anchor": {"x":0.5,"y":0.7}
},
"glassLemonAnim/glassAnimationLemon04":
{
	"frame": {"x":384,"y":1271,"w":116,"h":164},
	"rotated": false,
	"trimmed": true,
	"spriteSourceSize": {"x":0,"y":10,"w":116,"h":164},
	"sourceSize": {"w":119,"h":176},
	"anchor": {"x":0.5,"y":0.7}
},
"glassLemonAnim/glassAnimationLemon05":
{
	"frame": {"x":502,"y":1271,"w":116,"h":164},
	"rotated": false,
	"trimmed": true,
	"spriteSourceSize": {"x":0,"y":10,"w":116,"h":164},
	"sourceSize": {"w":119,"h":176},
	"anchor": {"x":0.5,"y":0.7}
},
"glassLemonAnim/glassAnimationLemon06":
{
	"frame": {"x":499,"y":910,"w":116,"h":164},
	"rotated": true,
	"trimmed": true,
	"spriteSourceSize": {"x":0,"y":10,"w":116,"h":164},
	"sourceSize": {"w":119,"h":176},
	"anchor": {"x":0.5,"y":0.7}
},
"glassLemonAnim/glassAnimationLemon07":
{
	"frame": {"x":1138,"y":652,"w":116,"h":164},
	"rotated": true,
	"trimmed": true,
	"spriteSourceSize": {"x":0,"y":10,"w":116,"h":164},
	"sourceSize": {"w":119,"h":176},
	"anchor": {"x":0.5,"y":0.7}
},
"glassLemonAnim/glassAnimationLemon08":
{
	"frame": {"x":1304,"y":651,"w":116,"h":164},
	"rotated": true,
	"trimmed": true,
	"spriteSourceSize": {"x":0,"y":10,"w":116,"h":164},
	"sourceSize": {"w":119,"h":176},
	"anchor": {"x":0.5,"y":0.7}
},
"glassLemonAnim/glassAnimationLemon09":
{
	"frame": {"x":665,"y":688,"w":116,"h":164},
	"rotated": true,
	"trimmed": true,
	"spriteSourceSize": {"x":0,"y":10,"w":116,"h":164},
	"sourceSize": {"w":119,"h":176},
	"anchor": {"x":0.5,"y":0.7}
},
"glassLemonAnim/glassAnimationLemon10":
{
	"frame": {"x":613,"y":1030,"w":116,"h":164},
	"rotated": true,
	"trimmed": true,
	"spriteSourceSize": {"x":0,"y":10,"w":116,"h":164},
	"sourceSize": {"w":119,"h":176},
	"anchor": {"x":0.5,"y":0.7}
},
"glassLemonAnim/glassAnimationLemon11":
{
	"frame": {"x":620,"y":1266,"w":116,"h":164},
	"rotated": false,
	"trimmed": true,
	"spriteSourceSize": {"x":0,"y":10,"w":116,"h":164},
	"sourceSize": {"w":119,"h":176},
	"anchor": {"x":0.5,"y":0.7}
},
"glassLemonAnim/glassAnimationLemon12":
{
	"frame": {"x":720,"y":1148,"w":116,"h":164},
	"rotated": true,
	"trimmed": true,
	"spriteSourceSize": {"x":0,"y":10,"w":116,"h":164},
	"sourceSize": {"w":119,"h":176},
	"anchor": {"x":0.5,"y":0.7}
},
"glassLemonAnim/glassAnimationLemon13":
{
	"frame": {"x":738,"y":1266,"w":116,"h":164},
	"rotated": false,
	"trimmed": true,
	"spriteSourceSize": {"x":0,"y":10,"w":116,"h":164},
	"sourceSize": {"w":119,"h":176},
	"anchor": {"x":0.5,"y":0.7}
},
"glassLemonAnim/glassAnimationLemon14":
{
	"frame": {"x":856,"y":1266,"w":116,"h":164},
	"rotated": false,
	"trimmed": true,
	"spriteSourceSize": {"x":0,"y":10,"w":116,"h":164},
	"sourceSize": {"w":119,"h":176},
	"anchor": {"x":0.5,"y":0.7}
},
"glassLemonAnim/glassAnimationLemon15":
{
	"frame": {"x":1138,"y":770,"w":116,"h":164},
	"rotated": true,
	"trimmed": true,
	"spriteSourceSize": {"x":0,"y":10,"w":116,"h":164},
	"sourceSize": {"w":119,"h":176},
	"anchor": {"x":0.5,"y":0.7}
},
"glassLemonAnim/glassAnimationLemon16":
{
	"frame": {"x":1304,"y":769,"w":116,"h":164},
	"rotated": true,
	"trimmed": true,
	"spriteSourceSize": {"x":0,"y":10,"w":116,"h":164},
	"sourceSize": {"w":119,"h":176},
	"anchor": {"x":0.5,"y":0.7}
},
"glassLemonAnim/glassAnimationLemon17":
{
	"frame": {"x":1592,"y":853,"w":116,"h":164},
	"rotated": true,
	"trimmed": true,
	"spriteSourceSize": {"x":0,"y":10,"w":116,"h":164},
	"sourceSize": {"w":119,"h":176},
	"anchor": {"x":0.5,"y":0.7}
},
"glassLemonAnim/glassAnimationLemon18":
{
	"frame": {"x":1758,"y":880,"w":116,"h":164},
	"rotated": true,
	"trimmed": true,
	"spriteSourceSize": {"x":0,"y":10,"w":116,"h":164},
	"sourceSize": {"w":119,"h":176},
	"anchor": {"x":0.5,"y":0.7}
},
"glassLemonAnim/glassAnimationLemon19":
{
	"frame": {"x":1304,"y":887,"w":116,"h":164},
	"rotated": true,
	"trimmed": true,
	"spriteSourceSize": {"x":0,"y":10,"w":116,"h":164},
	"sourceSize": {"w":119,"h":176},
	"anchor": {"x":0.5,"y":0.7}
},
"glassLemonAnim/glassAnimationLemon20":
{
	"frame": {"x":1592,"y":971,"w":116,"h":164},
	"rotated": true,
	"trimmed": true,
	"spriteSourceSize": {"x":0,"y":10,"w":116,"h":164},
	"sourceSize": {"w":119,"h":176},
	"anchor": {"x":0.5,"y":0.7}
},
"glassLemonAnim/glassAnimationLemon21":
{
	"frame": {"x":1758,"y":998,"w":116,"h":164},
	"rotated": true,
	"trimmed": true,
	"spriteSourceSize": {"x":0,"y":10,"w":116,"h":164},
	"sourceSize": {"w":119,"h":176},
	"anchor": {"x":0.5,"y":0.7}
},
"glassLemonAnim/glassAnimationLemon22":
{
	"frame": {"x":963,"y":794,"w":116,"h":164},
	"rotated": true,
	"trimmed": true,
	"spriteSourceSize": {"x":0,"y":10,"w":116,"h":164},
	"sourceSize": {"w":119,"h":176},
	"anchor": {"x":0.5,"y":0.7}
},
"glassLemonAnim/glassAnimationLemon23":
{
	"frame": {"x":1129,"y":888,"w":116,"h":164},
	"rotated": true,
	"trimmed": true,
	"spriteSourceSize": {"x":0,"y":10,"w":116,"h":164},
	"sourceSize": {"w":119,"h":176},
	"anchor": {"x":0.5,"y":0.7}
},
"glassLemonAnim/glassAnimationLemon24":
{
	"frame": {"x":1619,"y":499,"w":116,"h":169},
	"rotated": true,
	"trimmed": true,
	"spriteSourceSize": {"x":0,"y":5,"w":116,"h":169},
	"sourceSize": {"w":119,"h":176},
	"anchor": {"x":0.5,"y":0.7}
},
"glassLemonAnim/glassAnimationLemon25":
{
	"frame": {"x":1603,"y":735,"w":116,"h":172},
	"rotated": true,
	"trimmed": true,
	"spriteSourceSize": {"x":0,"y":2,"w":116,"h":172},
	"sourceSize": {"w":119,"h":176},
	"anchor": {"x":0.5,"y":0.7}
},
"glassLemonAnim/glassAnimationLemon26":
{
	"frame": {"x":547,"y":1148,"w":116,"h":171},
	"rotated": true,
	"trimmed": true,
	"spriteSourceSize": {"x":0,"y":3,"w":116,"h":171},
	"sourceSize": {"w":119,"h":176},
	"anchor": {"x":0.5,"y":0.7}
},
"glassLemonAnim/glassAnimationLemon27":
{
	"frame": {"x":1295,"y":1005,"w":116,"h":164},
	"rotated": true,
	"trimmed": true,
	"spriteSourceSize": {"x":0,"y":10,"w":116,"h":164},
	"sourceSize": {"w":119,"h":176},
	"anchor": {"x":0.5,"y":0.7}
},
"glassLemonAnim/glassAnimationLemon28":
{
	"frame": {"x":1619,"y":617,"w":116,"h":168},
	"rotated": true,
	"trimmed": true,
	"spriteSourceSize": {"x":0,"y":6,"w":116,"h":168},
	"sourceSize": {"w":119,"h":176},
	"anchor": {"x":0.5,"y":0.7}
},
"jugLemonAnim/jugAnimationLemon01":
{
	"frame": {"x":1470,"y":775,"w":120,"h":113},
	"rotated": false,
	"trimmed": true,
	"spriteSourceSize": {"x":20,"y":77,"w":120,"h":113},
	"sourceSize": {"w":162,"h":190},
	"anchor": {"x":0.5,"y":0.75}
},
"jugLemonAnim/jugAnimationLemon02":
{
	"frame": {"x":1470,"y":890,"w":120,"h":113},
	"rotated": false,
	"trimmed": true,
	"spriteSourceSize": {"x":20,"y":77,"w":120,"h":113},
	"sourceSize": {"w":162,"h":190},
	"anchor": {"x":0.5,"y":0.75}
},
"jugLemonAnim/jugAnimationLemon03":
{
	"frame": {"x":1461,"y":1121,"w":120,"h":113},
	"rotated": false,
	"trimmed": true,
	"spriteSourceSize": {"x":20,"y":77,"w":120,"h":113},
	"sourceSize": {"w":162,"h":190},
	"anchor": {"x":0.5,"y":0.75}
},
"jugLemonAnim/jugAnimationLemon04":
{
	"frame": {"x":1583,"y":1196,"w":120,"h":113},
	"rotated": false,
	"trimmed": true,
	"spriteSourceSize": {"x":20,"y":77,"w":120,"h":113},
	"sourceSize": {"w":162,"h":190},
	"anchor": {"x":0.5,"y":0.75}
},
"jugLemonAnim/jugAnimationLemon05":
{
	"frame": {"x":1707,"y":1116,"w":120,"h":113},
	"rotated": false,
	"trimmed": true,
	"spriteSourceSize": {"x":20,"y":77,"w":120,"h":113},
	"sourceSize": {"w":162,"h":190},
	"anchor": {"x":0.5,"y":0.75}
},
"jugLemonAnim/jugAnimationLemon06":
{
	"frame": {"x":1705,"y":1231,"w":120,"h":113},
	"rotated": false,
	"trimmed": true,
	"spriteSourceSize": {"x":20,"y":77,"w":120,"h":113},
	"sourceSize": {"w":162,"h":190},
	"anchor": {"x":0.5,"y":0.75}
},
"jugLemonAnim/jugAnimationLemon07":
{
	"frame": {"x":778,"y":899,"w":120,"h":113},
	"rotated": true,
	"trimmed": true,
	"spriteSourceSize": {"x":20,"y":77,"w":120,"h":113},
	"sourceSize": {"w":162,"h":190},
	"anchor": {"x":0.5,"y":0.75}
},
"jugLemonAnim/jugAnimationLemon08":
{
	"frame": {"x":779,"y":1021,"w":120,"h":113},
	"rotated": true,
	"trimmed": true,
	"spriteSourceSize": {"x":20,"y":77,"w":120,"h":113},
	"sourceSize": {"w":162,"h":190},
	"anchor": {"x":0.5,"y":0.75}
},
"jugLemonAnim/jugAnimationLemon09":
{
	"frame": {"x":894,"y":1008,"w":120,"h":113},
	"rotated": true,
	"trimmed": true,
	"spriteSourceSize": {"x":20,"y":77,"w":120,"h":113},
	"sourceSize": {"w":162,"h":190},
	"anchor": {"x":0.5,"y":0.75}
},
"jugLemonAnim/jugAnimationLemon10":
{
	"frame": {"x":1009,"y":1005,"w":120,"h":113},
	"rotated": true,
	"trimmed": true,
	"spriteSourceSize": {"x":20,"y":77,"w":120,"h":113},
	"sourceSize": {"w":162,"h":190},
	"anchor": {"x":0.5,"y":0.75}
},
"jugLemonAnim/jugAnimationLemon11":
{
	"frame": {"x":1124,"y":1006,"w":120,"h":113},
	"rotated": false,
	"trimmed": true,
	"spriteSourceSize": {"x":20,"y":77,"w":120,"h":113},
	"sourceSize": {"w":162,"h":190},
	"anchor": {"x":0.5,"y":0.75}
},
"jugLemonAnim/jugAnimationLemon12":
{
	"frame": {"x":1009,"y":1127,"w":120,"h":113},
	"rotated": false,
	"trimmed": true,
	"spriteSourceSize": {"x":20,"y":77,"w":120,"h":113},
	"sourceSize": {"w":162,"h":190},
	"anchor": {"x":0.5,"y":0.75}
},
"jugLemonAnim/jugAnimationLemon13":
{
	"frame": {"x":1131,"y":1121,"w":120,"h":113},
	"rotated": true,
	"trimmed": true,
	"spriteSourceSize": {"x":20,"y":77,"w":120,"h":113},
	"sourceSize": {"w":162,"h":190},
	"anchor": {"x":0.5,"y":0.75}
},
"jugLemonAnim/jugAnimationLemon14":
{
	"frame": {"x":974,"y":1242,"w":120,"h":113},
	"rotated": false,
	"trimmed": true,
	"spriteSourceSize": {"x":20,"y":77,"w":120,"h":113},
	"sourceSize": {"w":162,"h":190},
	"anchor": {"x":0.5,"y":0.75}
},
"jugLemonAnim/jugAnimationLemon15":
{
	"frame": {"x":1461,"y":1005,"w":120,"h":114},
	"rotated": false,
	"trimmed": true,
	"spriteSourceSize": {"x":20,"y":76,"w":120,"h":114},
	"sourceSize": {"w":162,"h":190},
	"anchor": {"x":0.5,"y":0.75}
},
"jugLemonAnim/jugAnimationLemon16":
{
	"frame": {"x":1096,"y":1243,"w":120,"h":113},
	"rotated": false,
	"trimmed": true,
	"spriteSourceSize": {"x":20,"y":77,"w":120,"h":113},
	"sourceSize": {"w":162,"h":190},
	"anchor": {"x":0.5,"y":0.75}
},
"jugLemonAnim/jugAnimationLemon17":
{
	"frame": {"x":1246,"y":1123,"w":120,"h":113},
	"rotated": false,
	"trimmed": true,
	"spriteSourceSize": {"x":20,"y":77,"w":120,"h":113},
	"sourceSize": {"w":162,"h":190},
	"anchor": {"x":0.5,"y":0.75}
},
"jugLemonAnim/jugAnimationLemon18":
{
	"frame": {"x":1218,"y":1243,"w":120,"h":113},
	"rotated": false,
	"trimmed": true,
	"spriteSourceSize": {"x":20,"y":77,"w":120,"h":113},
	"sourceSize": {"w":162,"h":190},
	"anchor": {"x":0.5,"y":0.75}
},
"jugLemonAnim/jugAnimationLemon19":
{
	"frame": {"x":831,"y":687,"w":130,"h":122},
	"rotated": false,
	"trimmed": true,
	"spriteSourceSize": {"x":11,"y":62,"w":130,"h":122},
	"sourceSize": {"w":162,"h":190},
	"anchor": {"x":0.5,"y":0.75}
},
"jugLemonAnim/jugAnimationLemon20":
{
	"frame": {"x":1470,"y":648,"w":131,"h":125},
	"rotated": false,
	"trimmed": true,
	"spriteSourceSize": {"x":11,"y":49,"w":131,"h":125},
	"sourceSize": {"w":162,"h":190},
	"anchor": {"x":0.5,"y":0.75}
},
"jugLemonAnim/jugAnimationLemon21":
{
	"frame": {"x":1790,"y":497,"w":139,"h":131},
	"rotated": false,
	"trimmed": true,
	"spriteSourceSize": {"x":5,"y":38,"w":139,"h":131},
	"sourceSize": {"w":162,"h":190},
	"anchor": {"x":0.5,"y":0.75}
},
"jugLemonAnim/jugAnimationLemon22":
{
	"frame": {"x":1793,"y":1,"w":145,"h":136},
	"rotated": false,
	"trimmed": true,
	"spriteSourceSize": {"x":4,"y":29,"w":145,"h":136},
	"sourceSize": {"w":162,"h":190},
	"anchor": {"x":0.5,"y":0.75}
},
"jugLemonAnim/jugAnimationLemon23":
{
	"frame": {"x":1462,"y":499,"w":155,"h":147},
	"rotated": false,
	"trimmed": true,
	"spriteSourceSize": {"x":1,"y":11,"w":155,"h":147},
	"sourceSize": {"w":162,"h":190},
	"anchor": {"x":0.5,"y":0.75}
},
"jugLemonAnim/jugAnimationLemon24":
{
	"frame": {"x":1786,"y":333,"w":162,"h":152},
	"rotated": true,
	"trimmed": true,
	"spriteSourceSize": {"x":0,"y":0,"w":162,"h":152},
	"sourceSize": {"w":162,"h":190},
	"anchor": {"x":0.5,"y":0.75}
},
"jugLemonAnim/jugAnimationLemon25":
{
	"frame": {"x":1138,"y":499,"w":160,"h":151},
	"rotated": false,
	"trimmed": true,
	"spriteSourceSize": {"x":2,"y":0,"w":160,"h":151},
	"sourceSize": {"w":162,"h":190},
	"anchor": {"x":0.5,"y":0.75}
},
"jugLemonAnim/jugAnimationLemon26":
{
	"frame": {"x":1300,"y":499,"w":160,"h":150},
	"rotated": false,
	"trimmed": true,
	"spriteSourceSize": {"x":2,"y":0,"w":160,"h":150},
	"sourceSize": {"w":162,"h":190},
	"anchor": {"x":0.5,"y":0.75}
},
"jugLemonAnim/jugAnimationLemon27":
{
	"frame": {"x":1,"y":1271,"w":158,"h":165},
	"rotated": false,
	"trimmed": true,
	"spriteSourceSize": {"x":3,"y":0,"w":158,"h":165},
	"sourceSize": {"w":162,"h":190},
	"anchor": {"x":0.5,"y":0.75}
},
"jugLemonAnim/jugAnimationLemon28":
{
	"frame": {"x":822,"y":499,"w":156,"h":186},
	"rotated": false,
	"trimmed": true,
	"spriteSourceSize": {"x":4,"y":1,"w":156,"h":186},
	"sourceSize": {"w":162,"h":190},
	"anchor": {"x":0.5,"y":0.75}
},
"jugLemonAnim/jugAnimationLemon29":
{
	"frame": {"x":499,"y":722,"w":160,"h":186},
	"rotated": false,
	"trimmed": true,
	"spriteSourceSize": {"x":0,"y":1,"w":160,"h":186},
	"sourceSize": {"w":162,"h":190},
	"anchor": {"x":0.5,"y":0.75}
},
"jugLemonAnim/jugAnimationLemon30":
{
	"frame": {"x":980,"y":499,"w":156,"h":185},
	"rotated": false,
	"trimmed": true,
	"spriteSourceSize": {"x":4,"y":1,"w":156,"h":185},
	"sourceSize": {"w":162,"h":190},
	"anchor": {"x":0.5,"y":0.75}
},
"jugLemonAnim/jugAnimationLemon31":
{
	"frame": {"x":333,"y":945,"w":160,"h":187},
	"rotated": false,
	"trimmed": true,
	"spriteSourceSize": {"x":0,"y":1,"w":160,"h":187},
	"sourceSize": {"w":162,"h":190},
	"anchor": {"x":0.5,"y":0.75}
},
"jugLemonAnim/jugAnimationLemon32":
{
	"frame": {"x":665,"y":499,"w":155,"h":187},
	"rotated": false,
	"trimmed": true,
	"spriteSourceSize": {"x":5,"y":1,"w":155,"h":187},
	"sourceSize": {"w":162,"h":190},
	"anchor": {"x":0.5,"y":0.75}
},
"lemonExplodeFrames/symbolLemonExplodeAnim0001":
{
	"frame": {"x":495,"y":1028,"w":116,"h":96},
	"rotated": false,
	"trimmed": true,
	"spriteSourceSize": {"x":45,"y":63,"w":116,"h":96},
	"sourceSize": {"w":229,"h":213},
	"anchor": {"x":0.458515,"y":0.516432}
},
"lemonExplodeFrames/symbolLemonExplodeAnim0002":
{
	"frame": {"x":894,"y":1130,"w":113,"h":110},
	"rotated": false,
	"trimmed": true,
	"spriteSourceSize": {"x":45,"y":55,"w":113,"h":110},
	"sourceSize": {"w":229,"h":213},
	"anchor": {"x":0.458515,"y":0.516432}
},
"lemonExplodeFrames/symbolLemonExplodeAnim0003":
{
	"frame": {"x":441,"y":1134,"w":135,"h":104},
	"rotated": true,
	"trimmed": true,
	"spriteSourceSize": {"x":36,"y":59,"w":135,"h":104},
	"sourceSize": {"w":229,"h":213},
	"anchor": {"x":0.458515,"y":0.516432}
},
"lemonExplodeFrames/symbolLemonExplodeAnim0004":
{
	"frame": {"x":1789,"y":630,"w":138,"h":116},
	"rotated": false,
	"trimmed": true,
	"spriteSourceSize": {"x":34,"y":53,"w":138,"h":116},
	"sourceSize": {"w":229,"h":213},
	"anchor": {"x":0.458515,"y":0.516432}
},
"lemonExplodeFrames/symbolLemonExplodeAnim0005":
{
	"frame": {"x":1827,"y":1315,"w":110,"h":92},
	"rotated": false,
	"trimmed": true,
	"spriteSourceSize": {"x":48,"y":65,"w":110,"h":92},
	"sourceSize": {"w":229,"h":213},
	"anchor": {"x":0.458515,"y":0.516432}
},
"lemonExplodeFrames/symbolLemonExplodeAnim0006":
{
	"frame": {"x":214,"y":499,"w":101,"h":85},
	"rotated": true,
	"trimmed": true,
	"spriteSourceSize": {"x":52,"y":68,"w":101,"h":85},
	"sourceSize": {"w":229,"h":213},
	"anchor": {"x":0.458515,"y":0.516432}
},
"lemonExplodeFrames/symbolLemonExplodeAnim0007":
{
	"frame": {"x":1144,"y":1358,"w":79,"h":70},
	"rotated": false,
	"trimmed": true,
	"spriteSourceSize": {"x":63,"y":76,"w":79,"h":70},
	"sourceSize": {"w":229,"h":213},
	"anchor": {"x":0.458515,"y":0.516432}
},
"lemonExplodeFrames/symbolLemonExplodeAnim0008":
{
	"frame": {"x":1008,"y":912,"w":103,"h":91},
	"rotated": false,
	"trimmed": true,
	"spriteSourceSize": {"x":51,"y":65,"w":103,"h":91},
	"sourceSize": {"w":229,"h":213},
	"anchor": {"x":0.458515,"y":0.516432}
},
"lemonExplodeFrames/symbolLemonExplodeAnim0009":
{
	"frame": {"x":665,"y":902,"w":126,"h":111},
	"rotated": true,
	"trimmed": true,
	"spriteSourceSize": {"x":39,"y":55,"w":126,"h":111},
	"sourceSize": {"w":229,"h":213},
	"anchor": {"x":0.458515,"y":0.516432}
},
"lemonExplodeFrames/symbolLemonExplodeAnim0010":
{
	"frame": {"x":1827,"y":1231,"w":111,"h":82},
	"rotated": false,
	"trimmed": true,
	"spriteSourceSize": {"x":51,"y":75,"w":111,"h":82},
	"sourceSize": {"w":229,"h":213},
	"anchor": {"x":0.458515,"y":0.516432}
},
"lemonExplodeFrames/symbolLemonExplodeAnim0011":
{
	"frame": {"x":1793,"y":139,"w":171,"h":137},
	"rotated": true,
	"trimmed": true,
	"spriteSourceSize": {"x":25,"y":48,"w":171,"h":137},
	"sourceSize": {"w":229,"h":213},
	"anchor": {"x":0.458515,"y":0.516432}
},
"lemonExplodeFrames/symbolLemonExplodeAnim0012":
{
	"frame": {"x":1,"y":1,"w":229,"h":193},
	"rotated": false,
	"trimmed": true,
	"spriteSourceSize": {"x":0,"y":20,"w":229,"h":193},
	"sourceSize": {"w":229,"h":213},
	"anchor": {"x":0.458515,"y":0.516432}
},
"lemonExplodeFrames/symbolLemonExplodeAnim0013":
{
	"frame": {"x":1,"y":196,"w":222,"h":199},
	"rotated": false,
	"trimmed": true,
	"spriteSourceSize": {"x":3,"y":10,"w":222,"h":199},
	"sourceSize": {"w":229,"h":213},
	"anchor": {"x":0.458515,"y":0.516432}
},
"lemonExplodeFrames/symbolLemonExplodeAnim0014":
{
	"frame": {"x":1,"y":397,"w":211,"h":203},
	"rotated": false,
	"trimmed": true,
	"spriteSourceSize": {"x":9,"y":0,"w":211,"h":203},
	"sourceSize": {"w":229,"h":213},
	"anchor": {"x":0.458515,"y":0.516432}
},
"lemonSwap":
{
	"frame": {"x":661,"y":806,"w":113,"h":94},
	"rotated": false,
	"trimmed": false,
	"spriteSourceSize": {"x":0,"y":0,"w":113,"h":94},
	"sourceSize": {"w":113,"h":94},
	"anchor": {"x":0.5,"y":0.5}
},
"match3GlassLemon/bubblesLemon01":
{
	"frame": {"x":1539,"y":1236,"w":34,"h":35},
	"rotated": false,
	"trimmed": true,
	"spriteSourceSize": {"x":62,"y":92,"w":34,"h":35},
	"sourceSize": {"w":113,"h":150},
	"anchor": {"x":0.5,"y":0.5}
},
"match3GlassLemon/bubblesLemon02":
{
	"frame": {"x":1246,"y":1006,"w":81,"h":36},
	"rotated": true,
	"trimmed": true,
	"spriteSourceSize": {"x":16,"y":83,"w":81,"h":36},
	"sourceSize": {"w":113,"h":150},
	"anchor": {"x":0.5,"y":0.5}
},
"match3GlassLemon/bubblesLemon03":
{
	"frame": {"x":1060,"y":1358,"w":82,"h":76},
	"rotated": false,
	"trimmed": true,
	"spriteSourceSize": {"x":16,"y":74,"w":82,"h":76},
	"sourceSize": {"w":113,"h":150},
	"anchor": {"x":0.5,"y":0.5}
},
"match3GlassLemon/bubblesLemon04":
{
	"frame": {"x":974,"y":1357,"w":84,"h":79},
	"rotated": false,
	"trimmed": true,
	"spriteSourceSize": {"x":15,"y":65,"w":84,"h":79},
	"sourceSize": {"w":113,"h":150},
	"anchor": {"x":0.5,"y":0.5}
},
"match3GlassLemon/bubblesLemon05":
{
	"frame": {"x":1424,"y":1348,"w":81,"h":80},
	"rotated": false,
	"trimmed": true,
	"spriteSourceSize": {"x":14,"y":56,"w":81,"h":80},
	"sourceSize": {"w":113,"h":150},
	"anchor": {"x":0.5,"y":0.5}
},
"match3GlassLemon/bubblesLemon06":
{
	"frame": {"x":1340,"y":1348,"w":82,"h":80},
	"rotated": false,
	"trimmed": true,
	"spriteSourceSize": {"x":17,"y":48,"w":82,"h":80},
	"sourceSize": {"w":113,"h":150},
	"anchor": {"x":0.5,"y":0.5}
},
"match3GlassLemon/bubblesLemon07":
{
	"frame": {"x":776,"y":811,"w":95,"h":86},
	"rotated": false,
	"trimmed": true,
	"spriteSourceSize": {"x":13,"y":31,"w":95,"h":86},
	"sourceSize": {"w":113,"h":150},
	"anchor": {"x":0.5,"y":0.5}
},
"match3GlassLemon/bubblesLemon08":
{
	"frame": {"x":1340,"y":1238,"w":108,"h":97},
	"rotated": true,
	"trimmed": true,
	"spriteSourceSize": {"x":5,"y":16,"w":108,"h":97},
	"sourceSize": {"w":113,"h":150},
	"anchor": {"x":0.5,"y":0.5}
},
"match3GlassLemon/bubblesLemon09":
{
	"frame": {"x":1439,"y":1236,"w":98,"h":105},
	"rotated": false,
	"trimmed": true,
	"spriteSourceSize": {"x":0,"y":7,"w":98,"h":105},
	"sourceSize": {"w":113,"h":150},
	"anchor": {"x":0.5,"y":0.5}
},
"match3GlassLemon/bubblesLemon10":
{
	"frame": {"x":1368,"y":1123,"w":91,"h":103},
	"rotated": false,
	"trimmed": true,
	"spriteSourceSize": {"x":15,"y":8,"w":91,"h":103},
	"sourceSize": {"w":113,"h":150},
	"anchor": {"x":0.5,"y":0.5}
},
"match3GlassLemon/bubblesLemon11":
{
	"frame": {"x":873,"y":811,"w":64,"h":86},
	"rotated": false,
	"trimmed": true,
	"spriteSourceSize": {"x":7,"y":0,"w":64,"h":86},
	"sourceSize": {"w":113,"h":150},
	"anchor": {"x":0.5,"y":0.5}
},
"match3GlassLemon/bubblesLemon12":
{
	"frame": {"x":1225,"y":1358,"w":54,"h":54},
	"rotated": false,
	"trimmed": true,
	"spriteSourceSize": {"x":25,"y":32,"w":54,"h":54},
	"sourceSize": {"w":113,"h":150},
	"anchor": {"x":0.5,"y":0.5}
},
"match3GlassLemon/match3GlassLemonDrainAnim01":
{
	"frame": {"x":232,"y":1,"w":164,"h":221},
	"rotated": true,
	"trimmed": true,
	"spriteSourceSize": {"x":0,"y":23,"w":164,"h":221},
	"sourceSize": {"w":164,"h":244},
	"anchor": {"x":0.5,"y":0.5}
},
"match3GlassLemon/match3GlassLemonDrainAnim02":
{
	"frame": {"x":1,"y":602,"w":164,"h":221},
	"rotated": false,
	"trimmed": true,
	"spriteSourceSize": {"x":0,"y":23,"w":164,"h":221},
	"sourceSize": {"w":164,"h":244},
	"anchor": {"x":0.5,"y":0.5}
},
"match3GlassLemon/match3GlassLemonDrainAnim03":
{
	"frame": {"x":455,"y":1,"w":164,"h":221},
	"rotated": true,
	"trimmed": true,
	"spriteSourceSize": {"x":0,"y":23,"w":164,"h":221},
	"sourceSize": {"w":164,"h":244},
	"anchor": {"x":0.5,"y":0.5}
},
"match3GlassLemon/match3GlassLemonDrainAnim04":
{
	"frame": {"x":1,"y":825,"w":164,"h":221},
	"rotated": false,
	"trimmed": true,
	"spriteSourceSize": {"x":0,"y":23,"w":164,"h":221},
	"sourceSize": {"w":164,"h":244},
	"anchor": {"x":0.5,"y":0.5}
},
"match3GlassLemon/match3GlassLemonDrainAnim05":
{
	"frame": {"x":678,"y":1,"w":164,"h":221},
	"rotated": true,
	"trimmed": true,
	"spriteSourceSize": {"x":0,"y":23,"w":164,"h":221},
	"sourceSize": {"w":164,"h":244},
	"anchor": {"x":0.5,"y":0.5}
},
"match3GlassLemon/match3GlassLemonDrainAnim06":
{
	"frame": {"x":1,"y":1048,"w":164,"h":221},
	"rotated": false,
	"trimmed": true,
	"spriteSourceSize": {"x":0,"y":23,"w":164,"h":221},
	"sourceSize": {"w":164,"h":244},
	"anchor": {"x":0.5,"y":0.5}
},
"match3GlassLemon/match3GlassLemonDrainAnim07":
{
	"frame": {"x":901,"y":1,"w":164,"h":221},
	"rotated": true,
	"trimmed": true,
	"spriteSourceSize": {"x":0,"y":23,"w":164,"h":221},
	"sourceSize": {"w":164,"h":244},
	"anchor": {"x":0.5,"y":0.5}
},
"match3GlassLemon/match3GlassLemonDrainAnim08":
{
	"frame": {"x":1124,"y":1,"w":164,"h":221},
	"rotated": true,
	"trimmed": true,
	"spriteSourceSize": {"x":0,"y":23,"w":164,"h":221},
	"sourceSize": {"w":164,"h":244},
	"anchor": {"x":0.5,"y":0.5}
},
"match3GlassLemon/match3GlassLemonDrainAnim09":
{
	"frame": {"x":1347,"y":1,"w":164,"h":221},
	"rotated": true,
	"trimmed": true,
	"spriteSourceSize": {"x":0,"y":23,"w":164,"h":221},
	"sourceSize": {"w":164,"h":244},
	"anchor": {"x":0.5,"y":0.5}
},
"match3GlassLemon/match3GlassLemonDrainAnim10":
{
	"frame": {"x":1570,"y":1,"w":164,"h":221},
	"rotated": true,
	"trimmed": true,
	"spriteSourceSize": {"x":0,"y":23,"w":164,"h":221},
	"sourceSize": {"w":164,"h":244},
	"anchor": {"x":0.5,"y":0.5}
},
"match3GlassLemon/match3GlassLemonDrainAnim11":
{
	"frame": {"x":167,"y":602,"w":164,"h":221},
	"rotated": false,
	"trimmed": true,
	"spriteSourceSize": {"x":0,"y":23,"w":164,"h":221},
	"sourceSize": {"w":164,"h":244},
	"anchor": {"x":0.5,"y":0.5}
},
"match3GlassLemon/match3GlassLemonDrainAnim12":
{
	"frame": {"x":167,"y":825,"w":164,"h":221},
	"rotated": false,
	"trimmed": true,
	"spriteSourceSize": {"x":0,"y":23,"w":164,"h":221},
	"sourceSize": {"w":164,"h":244},
	"anchor": {"x":0.5,"y":0.5}
},
"match3GlassLemon/match3GlassLemonDrainAnim13":
{
	"frame": {"x":167,"y":1048,"w":164,"h":221},
	"rotated": false,
	"trimmed": true,
	"spriteSourceSize": {"x":0,"y":23,"w":164,"h":221},
	"sourceSize": {"w":164,"h":244},
	"anchor": {"x":0.5,"y":0.5}
},
"match3GlassLemon/match3GlassLemonDrainAnim14":
{
	"frame": {"x":161,"y":1271,"w":164,"h":221},
	"rotated": true,
	"trimmed": true,
	"spriteSourceSize": {"x":0,"y":23,"w":164,"h":221},
	"sourceSize": {"w":164,"h":244},
	"anchor": {"x":0.5,"y":0.5}
},
"match3GlassLemon/match3GlassLemonDrainAnim15":
{
	"frame": {"x":232,"y":167,"w":164,"h":221},
	"rotated": true,
	"trimmed": true,
	"spriteSourceSize": {"x":0,"y":23,"w":164,"h":221},
	"sourceSize": {"w":164,"h":244},
	"anchor": {"x":0.5,"y":0.5}
},
"match3GlassLemon/match3GlassLemonDrainAnim16":
{
	"frame": {"x":455,"y":167,"w":164,"h":221},
	"rotated": true,
	"trimmed": true,
	"spriteSourceSize": {"x":0,"y":23,"w":164,"h":221},
	"sourceSize": {"w":164,"h":244},
	"anchor": {"x":0.5,"y":0.5}
},
"match3GlassLemon/match3GlassLemonDrainAnim17":
{
	"frame": {"x":678,"y":167,"w":164,"h":221},
	"rotated": true,
	"trimmed": true,
	"spriteSourceSize": {"x":0,"y":23,"w":164,"h":221},
	"sourceSize": {"w":164,"h":244},
	"anchor": {"x":0.5,"y":0.5}
},
"match3GlassLemon/match3GlassLemonDrainAnim18":
{
	"frame": {"x":901,"y":167,"w":164,"h":221},
	"rotated": true,
	"trimmed": true,
	"spriteSourceSize": {"x":0,"y":23,"w":164,"h":221},
	"sourceSize": {"w":164,"h":244},
	"anchor": {"x":0.5,"y":0.5}
},
"match3GlassLemon/match3GlassLemonDrainAnim19":
{
	"frame": {"x":1124,"y":167,"w":164,"h":221},
	"rotated": true,
	"trimmed": true,
	"spriteSourceSize": {"x":0,"y":23,"w":164,"h":221},
	"sourceSize": {"w":164,"h":244},
	"anchor": {"x":0.5,"y":0.5}
},
"match3GlassLemon/match3GlassLemonDrainAnim20":
{
	"frame": {"x":1347,"y":167,"w":164,"h":221},
	"rotated": true,
	"trimmed": true,
	"spriteSourceSize": {"x":0,"y":23,"w":164,"h":221},
	"sourceSize": {"w":164,"h":244},
	"anchor": {"x":0.5,"y":0.5}
},
"match3GlassLemon/match3GlassLemonDrainAnim21":
{
	"frame": {"x":1570,"y":167,"w":164,"h":221},
	"rotated": true,
	"trimmed": true,
	"spriteSourceSize": {"x":0,"y":23,"w":164,"h":221},
	"sourceSize": {"w":164,"h":244},
	"anchor": {"x":0.5,"y":0.5}
},
"match3GlassLemon/match3GlassLemonStaticAnim01":
{
	"frame": {"x":225,"y":333,"w":164,"h":221},
	"rotated": true,
	"trimmed": true,
	"spriteSourceSize": {"x":0,"y":23,"w":164,"h":221},
	"sourceSize": {"w":164,"h":244},
	"anchor": {"x":0.5,"y":0.5}
},
"match3GlassLemon/match3GlassLemonStaticAnim02":
{
	"frame": {"x":448,"y":333,"w":164,"h":221},
	"rotated": true,
	"trimmed": true,
	"spriteSourceSize": {"x":0,"y":23,"w":164,"h":221},
	"sourceSize": {"w":164,"h":244},
	"anchor": {"x":0.5,"y":0.5}
},
"match3GlassLemon/match3GlassLemonStaticAnim03":
{
	"frame": {"x":671,"y":333,"w":164,"h":221},
	"rotated": true,
	"trimmed": true,
	"spriteSourceSize": {"x":0,"y":23,"w":164,"h":221},
	"sourceSize": {"w":164,"h":244},
	"anchor": {"x":0.5,"y":0.5}
},
"match3GlassLemon/match3GlassLemonStaticAnim04":
{
	"frame": {"x":894,"y":333,"w":164,"h":221},
	"rotated": true,
	"trimmed": true,
	"spriteSourceSize": {"x":0,"y":23,"w":164,"h":221},
	"sourceSize": {"w":164,"h":244},
	"anchor": {"x":0.5,"y":0.5}
},
"match3GlassLemon/match3GlassLemonStaticAnim05":
{
	"frame": {"x":1117,"y":333,"w":164,"h":221},
	"rotated": true,
	"trimmed": true,
	"spriteSourceSize": {"x":0,"y":23,"w":164,"h":221},
	"sourceSize": {"w":164,"h":244},
	"anchor": {"x":0.5,"y":0.5}
},
"match3GlassLemon/match3GlassLemonStaticAnim06":
{
	"frame": {"x":1340,"y":333,"w":164,"h":221},
	"rotated": true,
	"trimmed": true,
	"spriteSourceSize": {"x":0,"y":23,"w":164,"h":221},
	"sourceSize": {"w":164,"h":244},
	"anchor": {"x":0.5,"y":0.5}
},
"match3GlassLemon/match3GlassLemonStaticAnim07":
{
	"frame": {"x":1563,"y":333,"w":164,"h":221},
	"rotated": true,
	"trimmed": true,
	"spriteSourceSize": {"x":0,"y":23,"w":164,"h":221},
	"sourceSize": {"w":164,"h":244},
	"anchor": {"x":0.5,"y":0.5}
},
"match3GlassLemon/match3GlassLemonStaticAnim08":
{
	"frame": {"x":333,"y":499,"w":164,"h":221},
	"rotated": false,
	"trimmed": true,
	"spriteSourceSize": {"x":0,"y":23,"w":164,"h":221},
	"sourceSize": {"w":164,"h":244},
	"anchor": {"x":0.5,"y":0.5}
},
"match3GlassLemon/match3GlassLemonStaticAnim09":
{
	"frame": {"x":333,"y":722,"w":164,"h":221},
	"rotated": false,
	"trimmed": true,
	"spriteSourceSize": {"x":0,"y":23,"w":164,"h":221},
	"sourceSize": {"w":164,"h":244},
	"anchor": {"x":0.5,"y":0.5}
},
"match3GlassLemon/match3GlassLemonStaticAnim10":
{
	"frame": {"x":499,"y":499,"w":164,"h":221},
	"rotated": false,
	"trimmed": true,
	"spriteSourceSize": {"x":0,"y":23,"w":164,"h":221},
	"sourceSize": {"w":164,"h":244},
	"anchor": {"x":0.5,"y":0.5}
},
"particle1Lemon":
{
	"frame": {"x":1281,"y":1358,"w":48,"h":48},
	"rotated": false,
	"trimmed": false,
	"spriteSourceSize": {"x":0,"y":0,"w":48,"h":48},
	"sourceSize": {"w":48,"h":48},
	"anchor": {"x":0.5,"y":0.5}
},
"particle2Lemon":
{
	"frame": {"x":1507,"y":1343,"w":43,"h":43},
	"rotated": false,
	"trimmed": false,
	"spriteSourceSize": {"x":0,"y":0,"w":43,"h":43},
	"sourceSize": {"w":43,"h":43},
	"anchor": {"x":0.5,"y":0.5}
},
"symbolSpecialLemonHorizontal":
{
	"frame": {"x":1829,"y":1116,"w":113,"h":94},
	"rotated": true,
	"trimmed": false,
	"spriteSourceSize": {"x":0,"y":0,"w":113,"h":94},
	"sourceSize": {"w":113,"h":94},
	"anchor": {"x":0.5,"y":0.5}
},
"symbolSpecialLemonVertical":
{
	"frame": {"x":893,"y":912,"w":113,"h":94},
	"rotated": false,
	"trimmed": false,
	"spriteSourceSize": {"x":0,"y":0,"w":113,"h":94},
	"sourceSize": {"w":113,"h":94},
	"anchor": {"x":0.5,"y":0.5}
}},
"animations": {
	"glassLemonAnim/glassAnimationLemon": ["glassLemonAnim/glassAnimationLemon01","glassLemonAnim/glassAnimationLemon02","glassLemonAnim/glassAnimationLemon03","glassLemonAnim/glassAnimationLemon04","glassLemonAnim/glassAnimationLemon05","glassLemonAnim/glassAnimationLemon06","glassLemonAnim/glassAnimationLemon07","glassLemonAnim/glassAnimationLemon08","glassLemonAnim/glassAnimationLemon09","glassLemonAnim/glassAnimationLemon10","glassLemonAnim/glassAnimationLemon11","glassLemonAnim/glassAnimationLemon12","glassLemonAnim/glassAnimationLemon13","glassLemonAnim/glassAnimationLemon14","glassLemonAnim/glassAnimationLemon15","glassLemonAnim/glassAnimationLemon16","glassLemonAnim/glassAnimationLemon17","glassLemonAnim/glassAnimationLemon18","glassLemonAnim/glassAnimationLemon19","glassLemonAnim/glassAnimationLemon20","glassLemonAnim/glassAnimationLemon21","glassLemonAnim/glassAnimationLemon22","glassLemonAnim/glassAnimationLemon23","glassLemonAnim/glassAnimationLemon24","glassLemonAnim/glassAnimationLemon25","glassLemonAnim/glassAnimationLemon26","glassLemonAnim/glassAnimationLemon27","glassLemonAnim/glassAnimationLemon28"],
	"jugLemonAnim/jugAnimationLemon": ["jugLemonAnim/jugAnimationLemon01","jugLemonAnim/jugAnimationLemon02","jugLemonAnim/jugAnimationLemon03","jugLemonAnim/jugAnimationLemon04","jugLemonAnim/jugAnimationLemon05","jugLemonAnim/jugAnimationLemon06","jugLemonAnim/jugAnimationLemon07","jugLemonAnim/jugAnimationLemon08","jugLemonAnim/jugAnimationLemon09","jugLemonAnim/jugAnimationLemon10","jugLemonAnim/jugAnimationLemon11","jugLemonAnim/jugAnimationLemon12","jugLemonAnim/jugAnimationLemon13","jugLemonAnim/jugAnimationLemon14","jugLemonAnim/jugAnimationLemon15","jugLemonAnim/jugAnimationLemon16","jugLemonAnim/jugAnimationLemon17","jugLemonAnim/jugAnimationLemon18","jugLemonAnim/jugAnimationLemon19","jugLemonAnim/jugAnimationLemon20","jugLemonAnim/jugAnimationLemon21","jugLemonAnim/jugAnimationLemon22","jugLemonAnim/jugAnimationLemon23","jugLemonAnim/jugAnimationLemon24","jugLemonAnim/jugAnimationLemon25","jugLemonAnim/jugAnimationLemon26","jugLemonAnim/jugAnimationLemon27","jugLemonAnim/jugAnimationLemon28","jugLemonAnim/jugAnimationLemon29","jugLemonAnim/jugAnimationLemon30","jugLemonAnim/jugAnimationLemon31","jugLemonAnim/jugAnimationLemon32"],
	"lemonExplodeFrames/symbolLemonExplodeAnim": ["lemonExplodeFrames/symbolLemonExplodeAnim0001","lemonExplodeFrames/symbolLemonExplodeAnim0002","lemonExplodeFrames/symbolLemonExplodeAnim0003","lemonExplodeFrames/symbolLemonExplodeAnim0004","lemonExplodeFrames/symbolLemonExplodeAnim0005","lemonExplodeFrames/symbolLemonExplodeAnim0006","lemonExplodeFrames/symbolLemonExplodeAnim0007","lemonExplodeFrames/symbolLemonExplodeAnim0008","lemonExplodeFrames/symbolLemonExplodeAnim0009","lemonExplodeFrames/symbolLemonExplodeAnim0010","lemonExplodeFrames/symbolLemonExplodeAnim0011","lemonExplodeFrames/symbolLemonExplodeAnim0012","lemonExplodeFrames/symbolLemonExplodeAnim0013","lemonExplodeFrames/symbolLemonExplodeAnim0014"],
	"match3GlassLemon/bubblesLemon": ["match3GlassLemon/bubblesLemon01","match3GlassLemon/bubblesLemon02","match3GlassLemon/bubblesLemon03","match3GlassLemon/bubblesLemon04","match3GlassLemon/bubblesLemon05","match3GlassLemon/bubblesLemon06","match3GlassLemon/bubblesLemon07","match3GlassLemon/bubblesLemon08","match3GlassLemon/bubblesLemon09","match3GlassLemon/bubblesLemon10","match3GlassLemon/bubblesLemon11","match3GlassLemon/bubblesLemon12"],
	"match3GlassLemon/match3GlassLemonDrainAnim": ["match3GlassLemon/match3GlassLemonDrainAnim01","match3GlassLemon/match3GlassLemonDrainAnim02","match3GlassLemon/match3GlassLemonDrainAnim03","match3GlassLemon/match3GlassLemonDrainAnim04","match3GlassLemon/match3GlassLemonDrainAnim05","match3GlassLemon/match3GlassLemonDrainAnim06","match3GlassLemon/match3GlassLemonDrainAnim07","match3GlassLemon/match3GlassLemonDrainAnim08","match3GlassLemon/match3GlassLemonDrainAnim09","match3GlassLemon/match3GlassLemonDrainAnim10","match3GlassLemon/match3GlassLemonDrainAnim11","match3GlassLemon/match3GlassLemonDrainAnim12","match3GlassLemon/match3GlassLemonDrainAnim13","match3GlassLemon/match3GlassLemonDrainAnim14","match3GlassLemon/match3GlassLemonDrainAnim15","match3GlassLemon/match3GlassLemonDrainAnim16","match3GlassLemon/match3GlassLemonDrainAnim17","match3GlassLemon/match3GlassLemonDrainAnim18","match3GlassLemon/match3GlassLemonDrainAnim19","match3GlassLemon/match3GlassLemonDrainAnim20","match3GlassLemon/match3GlassLemonDrainAnim21"],
	"match3GlassLemon/match3GlassLemonStaticAnim": ["match3GlassLemon/match3GlassLemonStaticAnim01","match3GlassLemon/match3GlassLemonStaticAnim02","match3GlassLemon/match3GlassLemonStaticAnim03","match3GlassLemon/match3GlassLemonStaticAnim04","match3GlassLemon/match3GlassLemonStaticAnim05","match3GlassLemon/match3GlassLemonStaticAnim06","match3GlassLemon/match3GlassLemonStaticAnim07","match3GlassLemon/match3GlassLemonStaticAnim08","match3GlassLemon/match3GlassLemonStaticAnim09","match3GlassLemon/match3GlassLemonStaticAnim10"]
},
"meta": {
	"app": "https://www.codeandweb.com/texturepacker",
	"version": "1.0",
	"image": "lemon0.png",
	"format": "RGBA8888",
	"size": {"w":1939,"h":1437},
	"scale": "1",
	"smartupdate": "$TexturePacker:SmartUpdate:0e811aafa271b1ef85d2ad78f9868671:95a20c4165c4afe8acfdbe4658f76b5e:ccbc857ae264a952015e9292b30c17fb$"
}
}
